unhash/__init__.py
unhash/core/__init__.py
unhash/tests/__init__.py
unhash/tests/test_1984.py
unhash-1.0.1.dist-info/licenses/LICENSE.txt
unhash-1.0.1.dist-info/METADATA
unhash-1.0.1.dist-info/WHEEL
unhash-1.0.1.dist-info/top_level.txt
unhash-1.0.1.dist-info/RECORD
